amapy_core/__init__.py
amapy_core/plugins.py
amapy_core/api/__init__.py
amapy_core/api/base_api.py
amapy_core/api/settings_api.py
amapy_core/api/utils.py
amapy_core/api/repo_api/__init__.py
amapy_core/api/repo_api/add.py
amapy_core/api/repo_api/debug.py
amapy_core/api/repo_api/diff.py
amapy_core/api/repo_api/discard.py
amapy_core/api/repo_api/download.py
amapy_core/api/repo_api/info.py
amapy_core/api/repo_api/init.py
amapy_core/api/repo_api/pull.py
amapy_core/api/repo_api/remote.py
amapy_core/api/repo_api/remove.py
amapy_core/api/repo_api/repo.py
amapy_core/api/repo_api/report.py
amapy_core/api/repo_api/status.py
amapy_core/api/repo_api/switch.py
amapy_core/api/repo_api/union.py
amapy_core/api/repo_api/update.py
amapy_core/api/repo_api/upload.py
amapy_core/api/repo_api/version.py
amapy_core/api/repo_api/tests/__init__.py
amapy_core/api/repo_api/tests/test_add.py
amapy_core/api/repo_api/tests/test_combine.py
amapy_core/api/repo_api/tests/test_repo.py
amapy_core/api/repo_api/tests/test_version.py
amapy_core/api/store_api/__init__.py
amapy_core/api/store_api/class_info.py
amapy_core/api/store_api/clone_asset.py
amapy_core/api/store_api/copy.py
amapy_core/api/store_api/fetch.py
amapy_core/api/store_api/find.py
amapy_core/api/store_api/hash_api.py
amapy_core/api/store_api/list.py
amapy_core/api/store_api/store.py
amapy_core/api/store_api/tests/__init__.py
amapy_core/api/store_api/tests/test_hash.py
amapy_core/api/templates/__init__.py
amapy_core/api/templates/base.html
amapy_core/api/templates/combine_template.html
amapy_core/api/templates/diff_template.html
amapy_core/api/templates/report_template.html
amapy_core/api/tests/__init__.py
amapy_core/api/tests/test_base_api.py
amapy_core/api/tests/e2e_tests/__init__.py
amapy_core/api/tests/e2e_tests/base_e2e.py
amapy_core/api/tests/e2e_tests/clone_e2e.py
amapy_core/asset/__init__.py
amapy_core/asset/asset.py
amapy_core/asset/asset_class.py
amapy_core/asset/asset_diff.py
amapy_core/asset/asset_handle.py
amapy_core-1.0.1.dist-info/METADATA
amapy_core-1.0.1.dist-info/WHEEL
amapy_core-1.0.1.dist-info/top_level.txt
amapy_core-1.0.1.dist-info/RECORD
